uml2py.py
uml2py-1.0.1.dist-info/LICENSE
uml2py-1.0.1.dist-info/METADATA
uml2py-1.0.1.dist-info/WHEEL
uml2py-1.0.1.dist-info/top_level.txt
uml2py-1.0.1.dist-info/RECORD
