Metadata-Version: 2.1
Name: uml2py
Version: 1.0.1
Summary: A converter from PlantUML class diagrams to python3 skeleton classes.
Home-page: https://github.com/pedroreissantos/uml2py
Author: Pedro Reis dos Santos
Author-email: reis.santos@tecnico.ulisboa.pt
License: MIT
Classifier: Programming Language :: Python :: 3
Classifier: License :: OSI Approved :: MIT License
Classifier: Operating System :: OS Independent
Classifier: Intended Audience :: Developers
Classifier: Topic :: Software Development :: Compilers
Classifier: Development Status :: 4 - Beta
Classifier: Environment :: Console
Requires-Python: >=3.8
License-File: LICENSE
Requires-Dist: plantuml
Requires-Dist: ply
